axon/__init__.py
axon/apps/__init__.py
axon/apps/base.py
axon/apps/console.py
axon/apps/interface.py
axon/apps/iperf.py
axon/apps/monitor.py
axon/apps/namespace.py
axon/apps/stats.py
axon/apps/tcpdump.py
axon/apps/traffic.py
axon/client/__init__.py
axon/client/axon_client.py
axon/client/axon_installer.py
axon/client/basic_traffic_controller.py
axon/client/datacenter_traffic_controller.py
axon/client/mesh_ping.py
axon/client/test.py
axon/client/traffic_controller.py
axon/client/traffic_elements.py
axon/client/utils.py
axon/common/__init__.py
axon/common/config.py
axon/common/consts.py
axon/common/exception.py
axon/common/utils.py
axon/controller/__init__.py
axon/controller/axon_rpyc_controller.py
axon/controller/windows/__init__.py
axon/controller/windows/axon_service.py
axon/db/__init__.py
axon/db/db_pool_manager.py
axon/db/record.py
axon/db/record_count.py
axon/db/recorder.py
axon/db/recorder_factory.py
axon/db/sql/__init__.py
axon/db/sql/base.py
axon/db/sql/repository.py
axon/db/sql/analytics/__init__.py
axon/db/sql/analytics/models.py
axon/db/sql/config/__init__.py
axon/db/sql/config/models.py
axon/db/wavefront/__init__.py
axon/db/wavefront/wavefront_client.py
axon/tests/__init__.py
axon/tests/base.py
axon/tests/unit/__init__.py
axon/tests/unit/test_axon.py
axon/tests/unit/apps/__init__.py
axon/tests/unit/apps/test_console.py
axon/tests/unit/apps/test_interface.py
axon/tests/unit/apps/test_iperf.py
axon/tests/unit/apps/test_monitor.py
axon/tests/unit/apps/test_namespace.py
axon/tests/unit/apps/test_stats.py
axon/tests/unit/apps/test_tcpdump.py
axon/tests/unit/apps/test_traffic.py
axon/tests/unit/client/test_axon_client.py
axon/tests/unit/client/test_basic_traffic_controller.py
axon/tests/unit/client/test_datacenter_traffic_controller.py
axon/tests/unit/client/test_traffic_controller.py
axon/tests/unit/client/test_traffic_elements.py
axon/tests/unit/collector/__init__.py
axon/tests/unit/controller/__init__.py
axon/tests/unit/controller/test_rpyc_controller.py
validation_app_engine-0.3.5.dev43.dist-info/AUTHORS
validation_app_engine-0.3.5.dev43.dist-info/LICENSE.txt
validation_app_engine-0.3.5.dev43.dist-info/METADATA
validation_app_engine-0.3.5.dev43.dist-info/NOTICE.txt
validation_app_engine-0.3.5.dev43.dist-info/WHEEL
validation_app_engine-0.3.5.dev43.dist-info/entry_points.txt
validation_app_engine-0.3.5.dev43.dist-info/pbr.json
validation_app_engine-0.3.5.dev43.dist-info/top_level.txt
validation_app_engine-0.3.5.dev43.dist-info/RECORD
