Metadata-Version: 2.1
Name: validation-app-engine
Version: 0.3.5.dev43
Summary: Validation App Engine
Home-page: UNKNOWN
Author: VMware Inc
Author-email: UNKNOWN
License: UNKNOWN
Platform: UNKNOWN
Classifier: License :: OSI Approved :: GNU General Public License v2 (GPLv2)
Classifier: Operating System :: POSIX :: Linux
Classifier: Programming Language :: Python
Classifier: Programming Language :: Python :: 2
Classifier: Programming Language :: Python :: 2.7
Classifier: Programming Language :: Python :: 3
Classifier: Programming Language :: Python :: 3.5
Requires-Dist: fabric (==2.4.0)
Requires-Dist: psutil (==5.6.6)
Requires-Dist: rpyc (==4.0.2)
Requires-Dist: six (>=1.10.0)
Requires-Dist: SQLAlchemy (>=1.3.0)
Requires-Dist: wavefront-sdk-python (==1.1.1)
Requires-Dist: wavefront-api-client (==2.33.15)
Requires-Dist: ipaddress ; (python_version=='2.7')
